LICENSE
MANIFEST.in
README.md
setup.py
django_genericimports.egg-info/PKG-INFO
django_genericimports.egg-info/SOURCES.txt
django_genericimports.egg-info/dependency_links.txt
django_genericimports.egg-info/not-zip-safe
django_genericimports.egg-info/requires.txt
django_genericimports.egg-info/top_level.txt
docs/Makefile
docs/source/conf.py
docs/source/configuration.rst
docs/source/featuresandrequirements.rst
docs/source/filtersandcallbacks.rst
docs/source/index.rst
docs/source/installing.rst
docs/source/introduction.rst
docs/source/reports.rst
genericimports/__init__.py
genericimports/admin.py
genericimports/admin_actions.py
genericimports/cms_app.py
genericimports/example_settings.py
genericimports/exceptions.py
genericimports/forms.py
genericimports/models.py
genericimports/parser.py
genericimports/tests.py
genericimports/urls.py
genericimports/views.py
genericimports/static/css/importhub.css
genericimports/templates/error.html
genericimports/templates/import.html
genericimports/templates/thanks.html