Metadata-Version: 1.1
Name: django-genericimports
Version: 0.1b6
Summary: Import any CSV or XLS file regardless of data types, headers or foreignkeys.
Home-page: http://github.com/clione/django-genericimports
Author: Oscar Carballal Prego
Author-email: oscar.carballal@gmail.com
License: BSD licence, see LICENSE file
Platform: UNKNOWN
Classifier: Development Status :: 4 - Beta
Classifier: Intended Audience :: Developers
Classifier: Framework :: Django
Classifier: Operating System :: POSIX :: Linux
Classifier: Operating System :: Unix
Classifier: License :: OSI Approved :: BSD License
Classifier: Programming Language :: Python :: 2.7
Classifier: Programming Language :: Python :: 3.3
Classifier: Programming Language :: Python :: 3.4
